langchain_sema4/__init__.py
langchain_sema4/_common.py
langchain_sema4/_prompts.py
langchain_sema4/py.typed
langchain_sema4/toolkits.py
langchain_sema4-0.2.0.dist-info/LICENSE
langchain_sema4-0.2.0.dist-info/METADATA
langchain_sema4-0.2.0.dist-info/WHEEL
langchain_sema4-0.2.0.dist-info/RECORD
