Metadata-Version: 2.1
Name: langchain-sema4
Version: 0.2.0
Summary: An integration package connecting Sema4 and LangChain
Home-page: https://github.com/langchain-ai/langchain-sema4
License: MIT
Requires-Python: >=3.9,<4.0
Classifier: License :: OSI Approved :: MIT License
Classifier: Programming Language :: Python :: 3
Classifier: Programming Language :: Python :: 3.9
Classifier: Programming Language :: Python :: 3.10
Classifier: Programming Language :: Python :: 3.11
Classifier: Programming Language :: Python :: 3.12
Requires-Dist: langchain-core (>=0.3,<0.4)
Requires-Dist: requests (>=2.31.0,<3.0.0)
Project-URL: Repository, https://github.com/langchain-ai/langchain-sema4
Project-URL: Source Code, https://github.com/langchain-ai/langchain-sema4/tree/main/libs/sema4
